{"data_mtime": 1702585720, "dep_lines": [23, 21, 22, 6, 7, 8, 9, 10, 11, 12, 13, 14, 15, 18, 20, 1, 1, 1, 1, 1, 1, 1, 1, 1, 1, 1, 1, 1, 1, 1, 1, 1, 1, 1, 1, 1, 1, 1, 1, 1, 1, 1, 1, 1, 1, 1, 1, 1, 1, 1], "dep_prios": [5, 5, 5, 10, 10, 5, 10, 10, 5, 10, 10, 5, 5, 5, 10, 5, 20, 20, 20, 20, 20, 20, 20, 20, 20, 20, 20, 20, 30, 30, 30, 30, 30, 30, 30, 30, 30, 30, 30, 30, 30, 30, 30, 30, 30, 30, 30, 30, 30, 30], "dependencies": ["zmq.eventloop.zmqstream", "jupyter_client.session", "tornado.ioloop", "asyncio", "atexit", "io", "os", "sys", "threading", "traceback", "warnings", "binascii", "collections", "typing", "zmq", "builtins", "types", "json", "pyexpat.model", "pprint", "string", "copy", "html", "pyexpat.errors", "functools", "re", "logging", "itertools", "_typeshed", "_warnings", "abc", "array", "asyncio.events", "asyncio.futures", "asyncio.tasks", "ctypes", "ipykernel.kernelbase", "jupyter_client", "mmap", "pickle", "tornado", "tornado.util", "typing_extensions", "zmq.backend", "zmq.error", "zmq.eventloop", "zmq.sugar", "zmq.sugar.attrsettr", "zmq.sugar.context", "zmq.sugar.socket"], "hash": "c92f2838da5f04b41ad2eb8ec9c9ce5d43443c21dad1b2e0435e08f4e21da31a", "id": "ipykernel.iostream", "ignore_all": true, "interface_hash": "3e9bb94d26693559920033740f1ff5e2e8c3080ea78835a1094f40a12db1d75e", "mtime": 1690959050, "options": {"allow_redefinition": false, "allow_untyped_globals": false, "always_false": [], "always_true": [], "bazel": false, "check_untyped_defs": false, "disable_bytearray_promotion": false, "disable_error_code": [], "disable_memoryview_promotion": false, "disabled_error_codes": [], "disallow_any_decorated": false, "disallow_any_explicit": false, "disallow_any_expr": false, "disallow_any_generics": false, "disallow_any_unimported": false, "disallow_incomplete_defs": false, "disallow_subclassing_any": false, "disallow_untyped_calls": false, "disallow_untyped_decorators": false, "disallow_untyped_defs": false, "enable_error_code": [], "enabled_error_codes": [], "follow_imports": "normal", "follow_imports_for_stubs": false, "ignore_errors": false, "ignore_missing_imports": false, "implicit_optional": false, "implicit_reexport": true, "local_partial_types": false, "mypyc": false, "platform": "darwin", "plugins": [], "strict_concatenate": false, "strict_equality": false, "strict_optional": true, "warn_no_return": true, "warn_return_any": false, "warn_unreachable": false, "warn_unused_ignores": false}, "path": "/Users/minhtri/Library/Python/3.11/lib/python/site-packages/ipykernel/iostream.py", "plugin_data": null, "size": 25177, "suppressed": [], "version_id": "1.1.1"}